mtmhdf/__init__.py
mtmhdf/_hdf4.py
mtmhdf/_hdf5.py
mtmhdf/_utils.py
mtmhdf/grid2dreader.py
mtmhdf/grid_modis_sin.py
mtmhdf/reader.py
mtmhdf-1.2.0.dist-info/licenses/LICENSE
mtmhdf-1.2.0.dist-info/METADATA
mtmhdf-1.2.0.dist-info/WHEEL
mtmhdf-1.2.0.dist-info/top_level.txt
mtmhdf-1.2.0.dist-info/RECORD
