Metadata-Version: 2.4
Name: mtmhdf
Version: 1.2.0
Summary: imutum's packages for HDF
License: MIT License
Classifier: Development Status :: 3 - Alpha
Classifier: Programming Language :: Python :: 3.11
Classifier: Intended Audience :: Developers
Classifier: License :: OSI Approved :: MIT License
Classifier: Operating System :: MacOS
Classifier: Operating System :: POSIX :: Linux
Classifier: Operating System :: Microsoft :: Windows
Requires-Python: >=3.11
License-File: LICENSE
Requires-Dist: pyhdf>=0.10.5
Requires-Dist: netcdf4>=1.6.5
Requires-Dist: numpy>=1.23.0
Dynamic: license-file
